dominant_color_detection/__init__.py
dominant_color_detection/dominant_color_detection.py
dominant_color_detection-0.1.1.dist-info/LICENSE.txt
dominant_color_detection-0.1.1.dist-info/METADATA
dominant_color_detection-0.1.1.dist-info/WHEEL
dominant_color_detection-0.1.1.dist-info/top_level.txt
dominant_color_detection-0.1.1.dist-info/RECORD
