Metadata-Version: 2.1
Name: dominant-color-detection
Version: 0.1.1
Summary: Detects dominant color of an image
Home-page: UNKNOWN
Author: Hynek Davídek
Author-email: hynek.davidek@biano.com
License: MIT
Keywords: image,color,detection,dominant,kmeans
Platform: UNKNOWN
Classifier: Development Status :: 3 - Alpha
Classifier: Intended Audience :: Developers
Classifier: Topic :: Software Development :: Libraries :: Python Modules
Classifier: License :: OSI Approved :: MIT License
Classifier: Programming Language :: Python :: 3
Classifier: Programming Language :: Python :: 3.6
Classifier: Programming Language :: Python :: 3.7
Classifier: Programming Language :: Python :: 3.8
Requires-Dist: numpy
Requires-Dist: Pillow
Requires-Dist: scikit-learn
